{"一目连":{"losing":16,"winning":16},"万年竹":{"losing":28,"winning":35},"三尾狐":{"losing":11,"winning":14},"丑时之女":{"losing":20,"winning":13},"两面佛":{"losing":24,"winning":18},"九命猫":{"losing":10,"winning":17},"书翁":{"losing":7,"winning":25},"二口女":{"losing":31,"winning":16},"以津真天":{"losing":15,"winning":17},"傀儡师":{"losing":13,"winning":10},"兔丸":{"losing":28,"winning":20},"兵俑":{"losing":40,"winning":32},"凤凰火":{"losing":54,"winning":31},"判官":{"losing":14,"winning":14},"匣中少女":{"losing":8,"winning":23},"卖药郎":{"losing":25,"winning":12},"古笼火":{"losing":29,"winning":17},"吸血姬":{"losing":42,"winning":25},"夜叉":{"losing":23,"winning":17},"大天狗":{"losing":19,"winning":28},"奴良陆生":{"losing":36,"winning":30},"妖刀姬":{"losing":19,"winning":18},"妖狐":{"losing":18,"winning":8},"妖琴师":{"losing":12,"winning":19},"姑获鸟":{"losing":21,"winning":22},"孟婆":{"losing":36,"winning":18},"小松丸":{"losing":27,"winning":33},"小袖之手":{"losing":19,"winning":12},"小鹿男":{"losing":16,"winning":17},"山兔":{"losing":38,"winning":40},"山童":{"losing":28,"winning":43},"山风":{"losing":13,"winning":25},"巫蛊师":{"losing":25,"winning":28},"座敷童子":{"losing":85,"winning":55},"弈":{"losing":21,"winning":12},"彼岸花":{"losing":11,"winning":16},"御馔津":{"losing":47,"winning":21},"惠比寿":{"losing":23,"winning":58},"数珠":{"losing":28,"winning":32},"日和坊":{"losing":23,"winning":57},"杀生丸":{"losing":0,"winning":2},"桃花妖":{"losing":49,"winning":41},"椒图":{"losing":11,"winning":9},"樱花妖":{"losing":27,"winning":57},"武士之灵":{"losing":18,"winning":15},"河童":{"losing":20,"winning":17},"海坊主":{"losing":43,"winning":41},"清姬":{"losing":15,"winning":16},"烟烟罗":{"losing":14,"winning":14},"犬夜叉":{"losing":1,"winning":0},"犬神":{"losing":26,"winning":47},"独眼小僧":{"losing":12,"winning":23},"狸猫":{"losing":32,"winning":24},"玉藻前":{"losing":17,"winning":22},"白狼":{"losing":16,"winning":16},"白童子":{"losing":23,"winning":21},"百目鬼":{"losing":38,"winning":55},"童女":{"losing":46,"winning":42},"童男":{"losing":24,"winning":12},"管狐":{"losing":18,"winning":16},"络新妇":{"losing":21,"winning":24},"般若":{"losing":45,"winning":41},"花鸟卷":{"losing":31,"winning":48},"茨木童子":{"losing":12,"winning":13},"荒":{"losing":9,"winning":15},"荒川之主":{"losing":13,"winning":10},"萤草":{"losing":63,"winning":34},"虫师":{"losing":44,"winning":34},"蜜桃\u0026芥子":{"losing":22,"winning":43},"蝴蝶精":{"losing":32,"winning":44},"觉":{"losing":27,"winning":21},"跳跳哥哥":{"losing":11,"winning":29},"跳跳妹妹":{"losing":24,"winning":18},"跳跳弟弟":{"losing":15,"winning":16},"辉夜姬":{"losing":73,"winning":81},"追月神":{"losing":49,"winning":89},"酒吞童子":{"losing":12,"winning":22},"金鱼姬":{"losing":18,"winning":19},"铁鼠":{"losing":19,"winning":13},"镰鼬":{"losing":42,"winning":51},"阎魔":{"losing":36,"winning":21},"阿香":{"losing":30,"winning":19},"雨女":{"losing":31,"winning":33},"雪女":{"losing":27,"winning":30},"雪童子":{"losing":33,"winning":38},"青坊主":{"losing":29,"winning":21},"青蛙瓷器":{"losing":23,"winning":13},"青行灯":{"losing":11,"winning":16},"面灵气":{"losing":3,"winning":10},"食发鬼":{"losing":52,"winning":51},"食梦貘":{"losing":32,"winning":37},"饿鬼":{"losing":30,"winning":9},"首无":{"losing":14,"winning":19},"骨女":{"losing":9,"winning":11},"鬼使白":{"losing":26,"winning":20},"鬼使黑":{"losing":19,"winning":22},"鬼女红叶":{"losing":14,"winning":15},"鬼灯":{"losing":33,"winning":20},"鲤鱼精":{"losing":20,"winning":14},"鸦天狗":{"losing":19,"winning":16},"鸩":{"losing":51,"winning":23},"黑童子":{"losing":38,"winning":38}}