{"5":{"一目连":{"losing":6,"winning":10},"万年竹":{"losing":14,"winning":23},"三尾狐":{"losing":7,"winning":6},"丑时之女":{"losing":15,"winning":9},"两面佛":{"losing":14,"winning":9},"九命猫":{"losing":8,"winning":7},"书翁":{"losing":5,"winning":12},"二口女":{"losing":20,"winning":6},"以津真天":{"losing":10,"winning":10},"傀儡师":{"losing":8,"winning":9},"兔丸":{"losing":21,"winning":14},"兵俑":{"losing":28,"winning":18},"凤凰火":{"losing":27,"winning":21},"判官":{"losing":9,"winning":8},"匣中少女":{"losing":4,"winning":14},"卖药郎":{"losing":11,"winning":4},"古笼火":{"losing":16,"winning":10},"吸血姬":{"losing":29,"winning":14},"夜叉":{"losing":14,"winning":9},"大天狗":{"losing":16,"winning":19},"奴良陆生":{"losing":28,"winning":20},"妖刀姬":{"losing":14,"winning":9},"妖狐":{"losing":11,"winning":4},"妖琴师":{"losing":9,"winning":9},"姑获鸟":{"losing":12,"winning":15},"孟婆":{"losing":18,"winning":15},"小松丸":{"losing":14,"winning":20},"小袖之手":{"losing":11,"winning":8},"小鹿男":{"losing":8,"winning":10},"山兔":{"losing":31,"winning":25},"山童":{"losing":17,"winning":28},"山风":{"losing":9,"winning":16},"巫蛊师":{"losing":16,"winning":19},"座敷童子":{"losing":54,"winning":35},"弈":{"losing":13,"winning":8},"彼岸花":{"losing":5,"winning":8},"御馔津":{"losing":29,"winning":12},"惠比寿":{"losing":16,"winning":39},"数珠":{"losing":18,"winning":18},"日和坊":{"losing":13,"winning":41},"桃花妖":{"losing":36,"winning":32},"椒图":{"losing":8,"winning":6},"樱花妖":{"losing":16,"winning":38},"武士之灵":{"losing":13,"winning":10},"河童":{"losing":12,"winning":12},"海坊主":{"losing":25,"winning":27},"清姬":{"losing":9,"winning":11},"烟烟罗":{"losing":7,"winning":9},"犬神":{"losing":20,"winning":36},"独眼小僧":{"losing":7,"winning":16},"狸猫":{"losing":19,"winning":13},"玉藻前":{"losing":11,"winning":14},"白狼":{"losing":8,"winning":5},"白童子":{"losing":13,"winning":11},"百目鬼":{"losing":22,"winning":31},"童女":{"losing":24,"winning":28},"童男":{"losing":12,"winning":6},"管狐":{"losing":10,"winning":12},"络新妇":{"losing":13,"winning":14},"般若":{"losing":35,"winning":27},"花鸟卷":{"losing":23,"winning":24},"茨木童子":{"losing":7,"winning":10},"荒":{"losing":4,"winning":5},"荒川之主":{"losing":6,"winning":7},"萤草":{"losing":36,"winning":20},"虫师":{"losing":22,"winning":18},"蜜桃\u0026芥子":{"losing":12,"winning":27},"蝴蝶精":{"losing":17,"winning":30},"觉":{"losing":13,"winning":12},"跳跳哥哥":{"losing":8,"winning":20},"跳跳妹妹":{"losing":21,"winning":9},"跳跳弟弟":{"losing":11,"winning":9},"辉夜姬":{"losing":47,"winning":43},"追月神":{"losing":28,"winning":49},"酒吞童子":{"losing":7,"winning":11},"金鱼姬":{"losing":15,"winning":15},"铁鼠":{"losing":11,"winning":7},"镰鼬":{"losing":25,"winning":28},"阎魔":{"losing":15,"winning":12},"阿香":{"losing":16,"winning":9},"雨女":{"losing":26,"winning":23},"雪女":{"losing":9,"winning":16},"雪童子":{"losing":25,"winning":22},"青坊主":{"losing":14,"winning":12},"青蛙瓷器":{"losing":14,"winning":10},"青行灯":{"losing":7,"winning":10},"食发鬼":{"losing":31,"winning":33},"食梦貘":{"losing":23,"winning":21},"饿鬼":{"losing":16,"winning":6},"首无":{"losing":7,"winning":11},"骨女":{"losing":3,"winning":7},"鬼使白":{"losing":19,"winning":12},"鬼使黑":{"losing":8,"winning":16},"鬼女红叶":{"losing":10,"winning":13},"鬼灯":{"losing":19,"winning":11},"鲤鱼精":{"losing":13,"winning":12},"鸦天狗":{"losing":10,"winning":10},"鸩":{"losing":29,"winning":16},"黑童子":{"losing":25,"winning":25}},"6":{"一目连":{"losing":12,"winning":9},"万年竹":{"losing":16,"winning":14},"三尾狐":{"losing":10,"winning":9},"丑时之女":{"losing":9,"winning":7},"两面佛":{"losing":13,"winning":13},"九命猫":{"losing":7,"winning":10},"书翁":{"losing":3,"winning":11},"二口女":{"losing":15,"winning":9},"以津真天":{"losing":6,"winning":4},"傀儡师":{"losing":5,"winning":4},"兔丸":{"losing":7,"winning":8},"兵俑":{"losing":22,"winning":19},"凤凰火":{"losing":28,"winning":19},"判官":{"losing":11,"winning":9},"匣中少女":{"losing":7,"winning":11},"卖药郎":{"losing":20,"winning":14},"古笼火":{"losing":17,"winning":8},"吸血姬":{"losing":16,"winning":17},"夜叉":{"losing":10,"winning":10},"大天狗":{"losing":5,"winning":15},"奴良陆生":{"losing":15,"winning":14},"妖刀姬":{"losing":9,"winning":9},"妖狐":{"losing":9,"winning":10},"妖琴师":{"losing":6,"winning":11},"姑获鸟":{"losing":14,"winning":11},"孟婆":{"losing":23,"winning":5},"小松丸":{"losing":14,"winning":18},"小袖之手":{"losing":12,"winning":7},"小鹿男":{"losing":6,"winning":13},"山兔":{"losing":17,"winning":21},"山童":{"losing":19,"winning":21},"山风":{"losing":6,"winning":9},"巫蛊师":{"losing":12,"winning":14},"座敷童子":{"losing":42,"winning":30},"弈":{"losing":11,"winning":10},"彼岸花":{"losing":8,"winning":10},"御馔津":{"losing":25,"winning":15},"惠比寿":{"losing":10,"winning":24},"数珠":{"losing":15,"winning":24},"日和坊":{"losing":13,"winning":30},"桃花妖":{"losing":19,"winning":15},"椒图":{"losing":8,"winning":6},"樱花妖":{"losing":18,"winning":24},"武士之灵":{"losing":6,"winning":8},"河童":{"losing":15,"winning":9},"海坊主":{"losing":26,"winning":20},"清姬":{"losing":9,"winning":10},"烟烟罗":{"losing":10,"winning":5},"犬神":{"losing":15,"winning":22},"独眼小僧":{"losing":7,"winning":7},"狸猫":{"losing":20,"winning":11},"玉藻前":{"losing":11,"winning":13},"白狼":{"losing":10,"winning":9},"白童子":{"losing":9,"winning":12},"百目鬼":{"losing":15,"winning":30},"童女":{"losing":31,"winning":24},"童男":{"losing":17,"winning":7},"管狐":{"losing":12,"winning":3},"络新妇":{"losing":12,"winning":10},"般若":{"losing":17,"winning":21},"花鸟卷":{"losing":15,"winning":31},"茨木童子":{"losing":6,"winning":5},"荒":{"losing":5,"winning":12},"荒川之主":{"losing":11,"winning":4},"萤草":{"losing":34,"winning":27},"虫师":{"losing":28,"winning":22},"蜜桃\u0026芥子":{"losing":17,"winning":23},"蝴蝶精":{"losing":19,"winning":21},"觉":{"losing":18,"winning":14},"跳跳哥哥":{"losing":9,"winning":17},"跳跳妹妹":{"losing":9,"winning":11},"跳跳弟弟":{"losing":6,"winning":12},"辉夜姬":{"losing":35,"winning":55},"追月神":{"losing":30,"winning":50},"酒吞童子":{"losing":6,"winning":17},"金鱼姬":{"losing":4,"winning":10},"铁鼠":{"losing":17,"winning":8},"镰鼬":{"losing":18,"winning":33},"阎魔":{"losing":26,"winning":17},"阿香":{"losing":23,"winning":16},"雨女":{"losing":9,"winning":14},"雪女":{"losing":22,"winning":20},"雪童子":{"losing":12,"winning":23},"青坊主":{"losing":17,"winning":13},"青蛙瓷器":{"losing":14,"winning":6},"青行灯":{"losing":6,"winning":9},"面灵气":{"losing":6,"winning":14},"食发鬼":{"losing":34,"winning":25},"食梦貘":{"losing":14,"winning":23},"饿鬼":{"losing":18,"winning":5},"首无":{"losing":12,"winning":7},"骨女":{"losing":10,"winning":4},"鬼使白":{"losing":7,"winning":10},"鬼使黑":{"losing":13,"winning":7},"鬼女红叶":{"losing":10,"winning":2},"鬼灯":{"losing":20,"winning":11},"鲤鱼精":{"losing":12,"winning":6},"鸦天狗":{"losing":15,"winning":10},"鸩":{"losing":25,"winning":12},"黑童子":{"losing":21,"winning":27}},"8":{"一目连":{"losing":13,"winning":9},"万年竹":{"losing":23,"winning":27},"三尾狐":{"losing":9,"winning":10},"丑时之女":{"losing":7,"winning":4},"两面佛":{"losing":14,"winning":16},"九命猫":{"losing":10,"winning":9},"书翁":{"losing":20,"winning":8},"二口女":{"losing":14,"winning":6},"以津真天":{"losing":8,"winning":14},"傀儡师":{"losing":21,"winning":6},"兔丸":{"losing":20,"winning":18},"兵俑":{"losing":18,"winning":21},"凤凰火":{"losing":28,"winning":12},"判官":{"losing":8,"winning":10},"匣中少女":{"losing":8,"winning":11},"卖药郎":{"losing":14,"winning":16},"古笼火":{"losing":12,"winning":17},"吸血姬":{"losing":20,"winning":18},"夜叉":{"losing":10,"winning":4},"大天狗":{"losing":12,"winning":12},"奴良陆生":{"losing":18,"winning":24},"妖刀姬":{"losing":5,"winning":14},"妖狐":{"losing":14,"winning":8},"妖琴师":{"losing":19,"winning":7},"姑获鸟":{"losing":11,"winning":6},"孟婆":{"losing":25,"winning":11},"小松丸":{"losing":10,"winning":20},"小袖之手":{"losing":9,"winning":6},"小鹿男":{"losing":16,"winning":8},"山兔":{"losing":29,"winning":18},"山童":{"losing":19,"winning":26},"山风":{"losing":6,"winning":12},"巫蛊师":{"losing":11,"winning":5},"座敷童子":{"losing":49,"winning":49},"弈":{"losing":14,"winning":10},"彼岸花":{"losing":5,"winning":12},"御馔津":{"losing":24,"winning":16},"惠比寿":{"losing":10,"winning":28},"数珠":{"losing":10,"winning":23},"日和坊":{"losing":13,"winning":25},"杀生丸":{"losing":1,"winning":16},"桃花妖":{"losing":24,"winning":21},"椒图":{"losing":9,"winning":11},"樱花妖":{"losing":17,"winning":51},"武士之灵":{"losing":11,"winning":7},"河童":{"losing":12,"winning":7},"海坊主":{"losing":24,"winning":24},"清姬":{"losing":4,"winning":7},"烟烟罗":{"losing":11,"winning":13},"犬夜叉":{"losing":8,"winning":6},"犬神":{"losing":18,"winning":27},"独眼小僧":{"losing":15,"winning":4},"狸猫":{"losing":19,"winning":18},"玉藻前":{"losing":11,"winning":8},"白狼":{"losing":16,"winning":14},"白童子":{"losing":16,"winning":16},"百目鬼":{"losing":21,"winning":33},"童女":{"losing":31,"winning":29},"童男":{"losing":11,"winning":13},"管狐":{"losing":11,"winning":8},"络新妇":{"losing":6,"winning":8},"般若":{"losing":29,"winning":30},"花鸟卷":{"losing":22,"winning":35},"茨木童子":{"losing":15,"winning":15},"荒":{"losing":9,"winning":10},"荒川之主":{"losing":10,"winning":5},"萤草":{"losing":47,"winning":28},"虫师":{"losing":30,"winning":31},"蜜桃\u0026芥子":{"losing":23,"winning":32},"蝴蝶精":{"losing":20,"winning":12},"觉":{"losing":11,"winning":4},"跳跳哥哥":{"losing":4,"winning":13},"跳跳妹妹":{"losing":10,"winning":10},"跳跳弟弟":{"losing":12,"winning":8},"辉夜姬":{"losing":39,"winning":50},"追月神":{"losing":35,"winning":61},"酒吞童子":{"losing":12,"winning":11},"金鱼姬":{"losing":13,"winning":18},"铁鼠":{"losing":17,"winning":9},"镰鼬":{"losing":25,"winning":27},"阎魔":{"losing":20,"winning":22},"阿香":{"losing":19,"winning":21},"雨女":{"losing":19,"winning":17},"雪女":{"losing":22,"winning":20},"雪童子":{"losing":14,"winning":9},"青坊主":{"losing":27,"winning":15},"青蛙瓷器":{"losing":12,"winning":10},"青行灯":{"losing":12,"winning":9},"面灵气":{"losing":11,"winning":10},"食发鬼":{"losing":32,"winning":32},"食梦貘":{"losing":22,"winning":21},"饿鬼":{"losing":16,"winning":10},"首无":{"losing":15,"winning":10},"骨女":{"losing":6,"winning":11},"鬼使白":{"losing":10,"winning":6},"鬼使黑":{"losing":18,"winning":13},"鬼女红叶":{"losing":13,"winning":12},"鬼灯":{"losing":25,"winning":12},"鲤鱼精":{"losing":17,"winning":12},"鸦天狗":{"losing":16,"winning":10},"鸩":{"losing":19,"winning":27},"黑童子":{"losing":10,"winning":25}},"9":{"一目连":{"losing":1,"winning":3},"万年竹":{"losing":7,"winning":4},"三尾狐":{"losing":0,"winning":1},"丑时之女":{"losing":1,"winning":1},"两面佛":{"losing":1,"winning":2},"九命猫":{"losing":4,"winning":2},"书翁":{"losing":1,"winning":3},"二口女":{"losing":2,"winning":1},"以津真天":{"losing":2,"winning":1},"傀儡师":{"losing":3,"winning":2},"兔丸":{"losing":4,"winning":3},"兵俑":{"losing":8,"winning":5},"凤凰火":{"losing":8,"winning":5},"判官":{"losing":4,"winning":0},"匣中少女":{"losing":2,"winning":4},"卖药郎":{"losing":2,"winning":3},"古笼火":{"losing":0,"winning":1},"吸血姬":{"losing":4,"winning":9},"夜叉":{"losing":0,"winning":1},"大天狗":{"losing":4,"winning":2},"奴良陆生":{"losing":6,"winning":3},"妖刀姬":{"losing":3,"winning":2},"妖狐":{"losing":1,"winning":2},"妖琴师":{"losing":4,"winning":4},"姑获鸟":{"losing":4,"winning":0},"孟婆":{"losing":1,"winning":3},"小松丸":{"losing":5,"winning":11},"小袖之手":{"losing":4,"winning":1},"小鹿男":{"losing":3,"winning":1},"山兔":{"losing":6,"winning":6},"山童":{"losing":5,"winning":1},"山风":{"losing":0,"winning":4},"巫蛊师":{"losing":2,"winning":4},"座敷童子":{"losing":8,"winning":10},"弈":{"losing":3,"winning":3},"彼岸花":{"losing":2,"winning":2},"御馔津":{"losing":7,"winning":7},"惠比寿":{"losing":3,"winning":9},"数珠":{"losing":7,"winning":3},"日和坊":{"losing":2,"winning":6},"杀生丸":{"losing":3,"winning":3},"桃花妖":{"losing":4,"winning":5},"椒图":{"losing":3,"winning":1},"樱花妖":{"losing":4,"winning":6},"武士之灵":{"losing":1,"winning":0},"河童":{"losing":1,"winning":5},"海坊主":{"losing":6,"winning":9},"清姬":{"losing":5,"winning":2},"烟烟罗":{"losing":3,"winning":3},"犬夜叉":{"losing":5,"winning":0},"犬神":{"losing":1,"winning":8},"独眼小僧":{"losing":3,"winning":1},"狸猫":{"losing":5,"winning":1},"玉藻前":{"losing":2,"winning":2},"白狼":{"losing":7,"winning":0},"白童子":{"losing":0,"winning":1},"百目鬼":{"losing":8,"winning":9},"童女":{"losing":7,"winning":6},"童男":{"losing":4,"winning":0},"管狐":{"losing":2,"winning":1},"络新妇":{"losing":3,"winning":4},"般若":{"losing":4,"winning":5},"花鸟卷":{"losing":6,"winning":7},"荒":{"losing":2,"winning":3},"荒川之主":{"losing":1,"winning":1},"萤草":{"losing":5,"winning":8},"虫师":{"losing":6,"winning":8},"蜜桃\u0026芥子":{"losing":5,"winning":7},"蝴蝶精":{"losing":3,"winning":6},"觉":{"losing":2,"winning":0},"跳跳哥哥":{"losing":1,"winning":2},"跳跳妹妹":{"losing":2,"winning":2},"跳跳弟弟":{"losing":6,"winning":0},"辉夜姬":{"losing":14,"winning":15},"追月神":{"losing":6,"winning":7},"酒吞童子":{"losing":1,"winning":0},"金鱼姬":{"losing":1,"winning":3},"铁鼠":{"losing":3,"winning":1},"镰鼬":{"losing":9,"winning":7},"阎魔":{"losing":1,"winning":5},"阿香":{"losing":5,"winning":5},"雨女":{"losing":5,"winning":9},"雪女":{"losing":6,"winning":4},"雪童子":{"losing":3,"winning":3},"青坊主":{"losing":3,"winning":3},"青蛙瓷器":{"losing":4,"winning":5},"青行灯":{"losing":2,"winning":2},"面灵气":{"losing":2,"winning":4},"食发鬼":{"losing":6,"winning":2},"食梦貘":{"losing":2,"winning":8},"饿鬼":{"losing":3,"winning":3},"首无":{"losing":3,"winning":1},"骨女":{"losing":3,"winning":1},"鬼使白":{"losing":3,"winning":2},"鬼使黑":{"losing":3,"winning":3},"鬼切":{"losing":0,"winning":1},"鬼女红叶":{"losing":4,"winning":0},"鬼灯":{"losing":5,"winning":3},"鲤鱼精":{"losing":5,"winning":3},"鸦天狗":{"losing":3,"winning":2},"鸩":{"losing":2,"winning":8},"黑童子":{"losing":4,"winning":4}},"A":{"一目连":{"losing":32,"winning":31},"万年竹":{"losing":60,"winning":68},"三尾狐":{"losing":26,"winning":26},"丑时之女":{"losing":32,"winning":21},"两面佛":{"losing":42,"winning":40},"九命猫":{"losing":29,"winning":28},"书翁":{"losing":29,"winning":34},"二口女":{"losing":51,"winning":22},"以津真天":{"losing":26,"winning":29},"傀儡师":{"losing":37,"winning":21},"兔丸":{"losing":52,"winning":43},"兵俑":{"losing":76,"winning":63},"凤凰火":{"losing":91,"winning":57},"判官":{"losing":32,"winning":27},"匣中少女":{"losing":21,"winning":40},"卖药郎":{"losing":47,"winning":37},"古笼火":{"losing":45,"winning":36},"吸血姬":{"losing":69,"winning":58},"夜叉":{"losing":34,"winning":24},"大天狗":{"losing":37,"winning":48},"奴良陆生":{"losing":67,"winning":61},"妖刀姬":{"losing":31,"winning":34},"妖狐":{"losing":35,"winning":24},"妖琴师":{"losing":38,"winning":31},"姑获鸟":{"losing":41,"winning":32},"孟婆":{"losing":67,"winning":34},"小松丸":{"losing":43,"winning":69},"小袖之手":{"losing":36,"winning":22},"小鹿男":{"losing":33,"winning":32},"山兔":{"losing":83,"winning":70},"山童":{"losing":60,"winning":76},"山风":{"losing":21,"winning":41},"巫蛊师":{"losing":41,"winning":42},"座敷童子":{"losing":153,"winning":124},"弈":{"losing":41,"winning":31},"彼岸花":{"losing":20,"winning":32},"御馔津":{"losing":85,"winning":50},"惠比寿":{"losing":39,"winning":100},"数珠":{"losing":50,"winning":68},"日和坊":{"losing":41,"winning":102},"杀生丸":{"losing":4,"winning":19},"桃花妖":{"losing":83,"winning":73},"椒图":{"losing":28,"winning":24},"樱花妖":{"losing":55,"winning":119},"武士之灵":{"losing":31,"winning":25},"河童":{"losing":40,"winning":33},"海坊主":{"losing":81,"winning":80},"清姬":{"losing":27,"winning":30},"烟烟罗":{"losing":31,"winning":30},"犬夜叉":{"losing":13,"winning":6},"犬神":{"losing":54,"winning":93},"独眼小僧":{"losing":32,"winning":28},"狸猫":{"losing":63,"winning":43},"玉藻前":{"losing":35,"winning":37},"白狼":{"losing":41,"winning":28},"白童子":{"losing":38,"winning":40},"百目鬼":{"losing":66,"winning":103},"童女":{"losing":93,"winning":87},"童男":{"losing":44,"winning":26},"管狐":{"losing":35,"winning":24},"络新妇":{"losing":34,"winning":36},"般若":{"losing":85,"winning":83},"花鸟卷":{"losing":66,"winning":97},"茨木童子":{"losing":28,"winning":30},"荒":{"losing":20,"winning":30},"荒川之主":{"losing":28,"winning":17},"萤草":{"losing":122,"winning":83},"虫师":{"losing":86,"winning":79},"蜜桃\u0026芥子":{"losing":57,"winning":89},"蝴蝶精":{"losing":59,"winning":69},"觉":{"losing":44,"winning":30},"跳跳哥哥":{"losing":22,"winning":52},"跳跳妹妹":{"losing":42,"winning":32},"跳跳弟弟":{"losing":35,"winning":29},"辉夜姬":{"losing":135,"winning":163},"追月神":{"losing":99,"winning":167},"酒吞童子":{"losing":26,"winning":39},"金鱼姬":{"losing":33,"winning":46},"铁鼠":{"losing":48,"winning":25},"镰鼬":{"losing":77,"winning":95},"阎魔":{"losing":62,"winning":56},"阿香":{"losing":63,"winning":51},"雨女":{"losing":59,"winning":63},"雪女":{"losing":59,"winning":60},"雪童子":{"losing":54,"winning":57},"青坊主":{"losing":61,"winning":43},"青蛙瓷器":{"losing":44,"winning":31},"青行灯":{"losing":27,"winning":30},"面灵气":{"losing":19,"winning":28},"食发鬼":{"losing":103,"winning":92},"食梦貘":{"losing":61,"winning":73},"饿鬼":{"losing":53,"winning":24},"首无":{"losing":37,"winning":29},"骨女":{"losing":22,"winning":23},"鬼使白":{"losing":39,"winning":30},"鬼使黑":{"losing":42,"winning":39},"鬼切":{"losing":0,"winning":1},"鬼女红叶":{"losing":37,"winning":27},"鬼灯":{"losing":69,"winning":37},"鲤鱼精":{"losing":47,"winning":33},"鸦天狗":{"losing":44,"winning":32},"鸩":{"losing":75,"winning":63},"黑童子":{"losing":60,"winning":81}}}