{
  "日和坊": [
    "日和坊",
    "晴天娃娃",
    "日和",
    "向日葵",
    "rhf"
  ],
  "犬神": [
    "犬神",
    "土狗",
    "柴犬",
    "大田狗",
    "哈士奇",
    "qs"
  ],
  "追月神": [
    "追月神",
    "追月",
    "zy",
    "zys"
  ],
  "蝴蝶精": [
    "蝴蝶精",
    "蝴蝶",
    "hdj"
  ],
  "惠比寿": [
    "惠比寿",
    "老头",
    "爷爷",
    "金鱼佬",
    "hbs"
  ],
  "食发鬼": [
    "食发鬼",
    "食发",
    "sfg"
  ],
  "樱花妖": [
    "樱花妖",
    "樱花",
    "yhy"
  ],
  "山风": [
    "山风",
    "豪猪",
    "岚",
    "sf"
  ],
  "童女": [
    "童女",
    "tnv",
    "tn"
  ],
  "匣中少女": [
    "匣中少女",
    "匣女",
    "匣子",
    "xzsn"
  ],
  "小松丸": [
    "小松丸",
    "小怂丸",
    "松",
    "xsw"
  ],
  "山童": [
    "山童",
    "shantong",
    "stong"
  ],
  "万年竹": [
    "万年竹",
    "竹子",
    "wnz"
  ],
  "跳跳哥哥": [
    "跳跳哥哥",
    "跳哥",
    "ttgg"
  ],
  "鸦天狗": [
    "鸦天狗",
    "ytg"
  ],
  "独眼小僧": [
    "独眼小僧",
    "小僧",
    "dyxs"
  ],
  "一目连": [
    "一目连",
    "连连",
    "一目",
    "风神",
    "小神龙",
    "yml"
  ],
  "鬼使黑": [
    "鬼使黑",
    "小黑",
    "大黑",
    "gsh"
  ],
  "花鸟卷": [
    "花鸟卷",
    "花鸟",
    "卷",
    "hn",
    "hnj"
  ],
  "清姬": [
    "清姬",
    "qj"
  ],
  "雪童子": [
    "雪童子",
    "雪童",
    "xtz"
  ],
  "青行灯": [
    "青行灯",
    "青灯",
    "灯姐",
    "灯",
    "淋淋",
    "吸魂灯",
    "吸",
    "qxd"
  ],
  "书翁": [
    "书翁",
    "sw"
  ],
  "巫蛊师": [
    "巫蛊师",
    "无故事",
    "wgs"
  ],
  "蜜桃&芥子": [
    "蜜桃&芥子",
    "蜜桃",
    "芥子",
    "介子",
    "屁桃",
    "mt",
    "jz",
    "mtjz"
  ],
  "河童": [
    "河童",
    "茨水童子",
    "茨水",
    "ht"
  ],
  "金鱼姬": [
    "金鱼姬",
    "金鱼",
    "征服世界",
    "jyj"
  ],
  "妖琴师": [
    "妖琴师",
    "妖琴",
    "琴师",
    "yq",
    "yqs"
  ],
  "以津真天": [
    "以津真天",
    "鸟妹",
    "以津",
    "yjzt"
  ],
  "烟烟罗": [
    "烟烟罗",
    "烟",
    "yyl"
  ],
  "小鹿男": [
    "小鹿男",
    "小鹿",
    "鹿",
    "xln"
  ],
  "彼岸花": [
    "彼岸花",
    "花花",
    "彼岸",
    "花",
    "bah"
  ],
  "桃花妖": [
    "桃花妖",
    "桃花",
    "桃发发",
    "thy"
  ],
  "骨女": [
    "骨女",
    "gn"
  ],
  "凤凰火": [
    "凤凰火",
    "凤凰",
    "火女",
    "fhh"
  ],
  "孟婆": [
    "孟婆",
    "锅",
    "牙牙",
    "mp"
  ],
  "狸猫": [
    "狸猫",
    "lm"
  ],
  "大天狗": [
    "大天狗",
    "天狗",
    "狗子",
    "狗",
    "dtg"
  ],
  "玉藻前": [
    "玉藻前",
    "大舅",
    "女装",
    "玉藻",
    "yzq"
  ],
  "觉": [
    "觉",
    "j"
  ],
  "两面佛": [
    "两面佛",
    "佛",
    "丑佛",
    "lmf"
  ],
  "管狐": [
    "管狐",
    "gh"
  ],
  "判官": [
    "判官",
    "pg"
  ],
  "椒图": [
    "椒图",
    "图图",
    "链子",
    "连链",
    "蚌壳",
    "焦土",
    "jt"
  ],
  "酒吞童子": [
    "酒吞童子",
    "酒吞",
    "鬼王",
    "混乱",
    "天邪鬼吞",
    "吞吞",
    "jt",
    "jttz"
  ],
  "三尾狐": [
    "三尾狐",
    "三尾",
    "swh"
  ],
  "九命猫": [
    "九命猫",
    "jmm"
  ],
  "百目鬼": [
    "百目鬼",
    "百目",
    "bmg"
  ],
  "白童子": [
    "白童子",
    "小小白",
    "btz"
  ],
  "夜叉": [
    "夜叉",
    "yc"
  ],
  "鬼女红叶": [
    "鬼女红叶",
    "红叶",
    "gnhy"
  ],
  "辉夜姬": [
    "辉夜姬",
    "辉夜",
    "竹筒",
    "煤气",
    "座敷童女",
    "挥叶鸡",
    "hyj",
    "hy"
  ],
  "首无": [
    "首无",
    "sw"
  ],
  "弈": [
    "弈",
    "奕老板",
    "老板",
    "围棋",
    "瘸子",
    "赌场",
    "断腿",
    "奕",
    "九段",
    "yi",
    "y"
  ],
  "茨木童子": [
    "茨木童子",
    "茨木",
    "魂10",
    "魂十",
    "地狱之手",
    "迁怒",
    "茨球球",
    "茨球",
    "cm",
    "cmtz"
  ],
  "妖刀姬": [
    "妖刀姬",
    "妖刀",
    "刀",
    "刀姐",
    "ydj"
  ],
  "傀儡师": [
    "傀儡师",
    "傀儡",
    "kls"
  ],
  "兔丸": [
    "兔丸",
    "tw"
  ],
  "姑获鸟": [
    "姑获鸟",
    "鸟姐",
    "非洲战神",
    "伞剑",
    "咕咕",
    "ghn"
  ],
  "雪女": [
    "雪女",
    "xn"
  ],
  "白狼": [
    "白狼",
    "bl"
  ],
  "数珠": [
    "数珠",
    "那个女孩",
    "打坐",
    "念珠",
    "属猪",
    "sz"
  ],
  "食梦貘": [
    "食梦貘",
    "睡猪",
    "猪",
    "smm"
  ],
  "络新妇": [
    "络新妇",
    "蜘蛛",
    "lxf"
  ],
  "丑时之女": [
    "丑时之女",
    "丑女",
    "cszn",
    "cn"
  ],
  "跳跳弟弟": [
    "跳跳弟弟",
    "跳弟",
    "变大",
    "ttdd"
  ],
  "青蛙瓷器": [
    "青蛙瓷器",
    "青蛙",
    "瓷器",
    "色子",
    "骰子",
    "赌神",
    "麻将",
    "qwcq",
    "qw"
  ],
  "镰鼬": [
    "镰鼬",
    "老鼠",
    "鼠",
    "三兄弟",
    "炼油",
    "ly"
  ],
  "鬼使白": [
    "鬼使白",
    "小白",
    "gsb"
  ],
  "黑童子": [
    "黑童子",
    "小小黑",
    "htz"
  ],
  "山兔": [
    "山兔",
    "兔子",
    "二速",
    "双拉",
    "吼啦",
    "hoya",
    "stu",
    "st"
  ],
  "小袖之手": [
    "小袖之手",
    "小袖",
    "xxzs"
  ],
  "荒": [
    "荒",
    "荒总",
    "流星",
    "神使",
    "h"
  ],
  "阎魔": [
    "阎魔",
    "包子",
    "ym"
  ],
  "青坊主": [
    "青坊主",
    "qfz"
  ],
  "般若": [
    "般若",
    "封印",
    "嫉妒",
    "万物之父",
    "菠萝",
    "br"
  ],
  "饿鬼": [
    "饿鬼",
    "eg"
  ],
  "海坊主": [
    "海坊主",
    "鱼头",
    "hfz"
  ],
  "虫师": [
    "虫师",
    "cs"
  ],
  "妖狐": [
    "妖狐",
    "脸狐",
    "yh"
  ],
  "武士之灵": [
    "武士之灵",
    "wszl"
  ],
  "鬼灯": [
    "鬼灯",
    "冷彻",
    "冷撤",
    "gd"
  ],
  "阿香": [
    "阿香",
    "ax"
  ],
  "卖药郎": [
    "卖药郎",
    "药郎",
    "看破",
    "天平",
    "myl"
  ],
  "荒川之主": [
    "荒川之主",
    "荒川",
    "咸鱼",
    "咸鱼王",
    "hczz"
  ],
  "雨女": [
    "雨女",
    "假哭",
    "影帝",
    "yn"
  ],
  "古笼火": [
    "古笼火",
    "glh"
  ],
  "童男": [
    "童男",
    "献祭",
    "tnan"
  ],
  "跳跳妹妹": [
    "跳跳妹妹",
    "跳妹",
    "ttmm"
  ],
  "铁鼠": [
    "铁鼠",
    "钱鼠",
    "ts"
  ],
  "奴良陆生": [
    "奴良陆生",
    "陆生",
    "少主",
    "露胸",
    "nlls"
  ],
  "鲤鱼精": [
    "鲤鱼精",
    "鲤鱼",
    "lyj"
  ],
  "二口女": [
    "二口女",
    "二口",
    "ekn"
  ],
  "萤草": [
    "萤草",
    "樱草",
    "莹草",
    "草",
    "草爹",
    "yc"
  ],
  "鸩": [
    "鸩",
    "鸠",
    "z"
  ],
  "御馔津": [
    "御馔津",
    "骑驴",
    "达摩",
    "金达摩",
    "浴巾",
    "驴",
    "yzj"
  ],
  "座敷童子": [
    "座敷童子",
    "火",
    "打火机",
    "座敷",
    "火机",
    "zftz"
  ],
  "吸血姬": [
    "吸血姬",
    "xxj"
  ],
  "兵俑": [
    "兵俑",
    "兵勇",
    "兵佣",
    "by"
  ],
  "面灵气": [
    "面灵气",
    "m07",
    "灭淋器",
    "面具",
    "七面",
    "mlq"
  ],
  "犬夜叉": [
    "犬夜叉",
    "大狗",
    "qyc"
  ],
  "杀生丸": [
    "杀生丸",
    "二狗",
    "ssw"
  ],
  "鬼切": [
    "鬼切",
    "gq"
  ]
}
