{"一反木绵":-1,"一目连":-1,"万年竹":1,"三尾狐":1,"不知火":-2,"丑时之女":-1,"两面佛":1,"久次良":1,"九命猫":-1,"书翁":1,"二口女":1,"云外镜":2,"人面树":1,"以津真天":1,"傀儡师":-1,"兔丸":1,"入殓师":2,"八岐大蛇":2,"兵俑":-1,"凤凰火":2,"判官":1,"化鲸":-2,"匣中少女":2,"卖药郎":-1,"古笼火":-1,"吸血姬":1,"夜叉":2,"大天狗":-4,"大岳丸":2,"天井下":-1,"天剑韧心鬼切":-1,"奴良陆生":1,"妖刀姬":-1,"妖狐":-2,"妖琴师":1,"姑获鸟":1,"孟婆":-2,"小松丸":-4,"小袖之手":-7,"小鹿男":-3,"少羽大天狗":-3,"山兔":-3,"山童":-1,"山风":-2,"巫蛊师":-2,"座敷童子":1,"弈":-1,"彼岸花":5,"御怨般若":-1,"御馔津":-3,"惠比寿":-3,"数珠":-1,"於菊虫":4,"日和坊":1,"星熊童子":-3,"朽木露琪亚":-1,"杀生丸":-1,"桃花妖":-1,"桔梗":1,"椒图":-4,"樱花妖":1,"武士之灵":-2,"河童":-2,"泷夜叉姬":1,"海坊主":-1,"海忍":-1,"清姬":3,"炼狱茨木童子":-4,"烟烟罗":-2,"烬天玉藻前":2,"犬夜叉":1,"犬神":-3,"独眼小僧":5,"狸猫":1,"猫掌柜":1,"玉藻前":-2,"白狼":-2,"白童子":-2,"白藏主":-5,"百目鬼":1,"稻荷神御馔津":-1,"童女":-1,"童男":-1,"管狐":1,"纸舞":2,"络新妇":-1,"缘结神":1,"聆海金鱼姬":4,"般若":2,"花鸟卷":1,"苍风一目连":-4,"茨木童子":-4,"荒":3,"荒川之主":-1,"萤草":1,"薰":-1,"虫师":1,"蜜桃\u0026芥子":1,"蝴蝶精":2,"蟹姬":2,"觉":3,"赤影妖刀姬":-2,"跳跳哥哥":-1,"跳跳妹妹":-3,"跳跳弟弟":3,"辉夜姬":-1,"追月神":1,"酒吞童子":4,"金鱼姬":-1,"铁鼠":-4,"镰鼬":2,"阎魔":-2,"阿香":-2,"雨女":-1,"雪女":2,"雪童子":1,"青坊主":-1,"青蛙瓷器":1,"青行灯":-1,"面灵气":1,"风狸":1,"食发鬼":1,"食梦貘":-4,"饿鬼":2,"首无":-1,"骁浪荒川之主":-2,"骨女":-5,"鬼使白":1,"鬼使黑":1,"鬼切":-3,"鬼女红叶":2,"鬼灯":-3,"鬼王酒吞童子":2,"鬼童丸":4,"鲤鱼精":-2,"鸦天狗":1,"鸩":-1,"黑崎一护":-1,"黑童子":1}